easy_email_downloader/__init__.py
easy_email_downloader/_version.py
easy_email_downloader/common.py
easy_email_downloader/exceptions.py
easy_email_downloader/models.py
easy_email_downloader/py.typed
easy_email_downloader/utils.py
easy_email_downloader-2.0.0.dist-info/LICENSE.md
easy_email_downloader-2.0.0.dist-info/WHEEL
easy_email_downloader-2.0.0.dist-info/METADATA
easy_email_downloader-2.0.0.dist-info/RECORD
