Metadata-Version: 2.1
Name: easy-email-downloader
Version: 2.0.0
Summary: 
Home-page: https://github.com/dtomlinson91/easy-email-downloader
License: ISC
Keywords: email,download,imap
Author: Daniel Tomlinson
Author-email: dtomlinson@panaetius.co.uk
Requires-Python: >=3.8,<4.0
Classifier: License :: OSI Approved
Classifier: Programming Language :: Python :: 3
Classifier: Programming Language :: Python :: 3.10
Classifier: Programming Language :: Python :: 3.8
Classifier: Programming Language :: Python :: 3.9
Project-URL: Documentation, https://github.com/dtomlinson91/easy-email-downloader
Project-URL: Repository, https://github.com/dtomlinson91/easy-email-downloader
